{
  "source_csv": "IN/SPOD/ORG_UNIT_V20 20-03 v0.csv",
  "columns": [
    "TB_CODE",
    "TB_FULL_NAME",
    "TB_SHORT_NAME",
    "GOSB_CODE",
    "GOSB_NAME",
    "GOSB_SHORT_NAME",
    "CLUSTER_CODE",
    "GROUPING_CODE",
    "GOSB_CNT",
    "GROUPING_CNT",
    "ORG_UNIT_CODE"
  ],
  "rows": [
    {
      "TB_CODE": "18",
      "TB_FULL_NAME": "Байкальский банк",
      "TB_SHORT_NAME": "ББ",
      "GOSB_CODE": "0",
      "GOSB_NAME": "Аппарат территориального банка",
      "GOSB_SHORT_NAME": "Аппарат ББ",
      "CLUSTER_CODE": "0",
      "GROUPING_CODE": "1",
      "GOSB_CNT": "0",
      "GROUPING_CNT": "0",
      "ORG_UNIT_CODE": "10016438"
    },
    {
      "TB_CODE": "18",
      "TB_FULL_NAME": "Байкальский банк",
      "TB_SHORT_NAME": "ББ",
      "GOSB_CODE": "1802",
      "GOSB_NAME": "Аппарат Байкальского Банка",
      "GOSB_SHORT_NAME": "ЦПКК ББ",
      "CLUSTER_CODE": "1",
      "GROUPING_CODE": "1",
      "GOSB_CNT": "7",
      "GROUPING_CNT": "7",
      "ORG_UNIT_CODE": "10353225"
    },
    {
      "TB_CODE": "18",
      "TB_FULL_NAME": "Байкальский банк",
      "TB_SHORT_NAME": "ББ",
      "GOSB_CODE": "8586",
      "GOSB_NAME": "Иркутское ГОСБ",
      "GOSB_SHORT_NAME": "ГОСБ",
      "CLUSTER_CODE": "1",
      "GROUPING_CODE": "1",
      "GOSB_CNT": "27",
      "GROUPING_CNT": "27",
      "ORG_UNIT_CODE": "10037967"
    },
    {
      "TB_CODE": "18",
      "TB_FULL_NAME": "Байкальский банк",
      "TB_SHORT_NAME": "ББ",
      "GOSB_CODE": "8600",
      "GOSB_NAME": "Читинское ГОСБ",
      "GOSB_SHORT_NAME": "ГОСБ",
      "CLUSTER_CODE": "3",
      "GROUPING_CODE": "1",
      "GOSB_CNT": "6",
      "GROUPING_CNT": "6",
      "ORG_UNIT_CODE": "10016635"
    },
    {
      "TB_CODE": "18",
      "TB_FULL_NAME": "Байкальский банк",
      "TB_SHORT_NAME": "ББ",
      "GOSB_CODE": "8601",
      "GOSB_NAME": "Бурятское ГОСБ",
      "GOSB_SHORT_NAME": "ГОСБ",
      "CLUSTER_CODE": "4",
      "GROUPING_CODE": "1",
      "GOSB_CNT": "6",
      "GROUPING_CNT": "6",
      "ORG_UNIT_CODE": "10016634"
    },
    {
      "TB_CODE": "18",
      "TB_FULL_NAME": "Байкальский банк",
      "TB_SHORT_NAME": "ББ",
      "GOSB_CODE": "8603",
      "GOSB_NAME": "Якутское ГОСБ",
      "GOSB_SHORT_NAME": "ГОСБ",
      "CLUSTER_CODE": "2",
      "GROUPING_CODE": "1",
      "GOSB_CNT": "7",
      "GROUPING_CNT": "7",
      "ORG_UNIT_CODE": "10164582"
    },
    {
      "TB_CODE": "42",
      "TB_FULL_NAME": "Волго-Вятский банк",
      "TB_SHORT_NAME": "ВВБ",
      "GOSB_CODE": "0",
      "GOSB_NAME": "Аппарат территориального банка",
      "GOSB_SHORT_NAME": "Аппарат ВВБ",
      "CLUSTER_CODE": "0",
      "GROUPING_CODE": "1",
      "GOSB_CNT": "0",
      "GROUPING_CNT": "0",
      "ORG_UNIT_CODE": "10037179"
    },
    {
      "TB_CODE": "42",
      "TB_FULL_NAME": "Волго-Вятский банк",
      "TB_SHORT_NAME": "ВВБ",
      "GOSB_CODE": "4200",
      "GOSB_NAME": "Аппарат Волго-Вятского банка",
      "GOSB_SHORT_NAME": "ЦПКК ВВБ",
      "CLUSTER_CODE": "1",
      "GROUPING_CODE": "1",
      "GOSB_CNT": "15",
      "GROUPING_CNT": "15",
      "ORG_UNIT_CODE": "10299006"
    },
    {
      "TB_CODE": "42",
      "TB_FULL_NAME": "Волго-Вятский банк",
      "TB_SHORT_NAME": "ВВБ",
      "GOSB_CODE": "6984",
      "GOSB_NAME": "Пермское ГОСБ",
      "GOSB_SHORT_NAME": "ГОСБ",
      "CLUSTER_CODE": "1",
      "GROUPING_CODE": "1",
      "GOSB_CNT": "21",
      "GROUPING_CNT": "21",
      "ORG_UNIT_CODE": "10266200"
    },
    {
      "TB_CODE": "42",
      "TB_FULL_NAME": "Волго-Вятский банк",
      "TB_SHORT_NAME": "ВВБ",
      "GOSB_CODE": "8589",
      "GOSB_NAME": "Мордовское ГОСБ",
      "GOSB_SHORT_NAME": "ГОСБ",
      "CLUSTER_CODE": "4",
      "GROUPING_CODE": "1",
      "GOSB_CNT": "6",
      "GROUPING_CNT": "6",
      "ORG_UNIT_CODE": "10016725"
    },
    {
      "TB_CODE": "42",
      "TB_FULL_NAME": "Волго-Вятский банк",
      "TB_SHORT_NAME": "ВВБ",
      "GOSB_CODE": "8610",
      "GOSB_NAME": "Банк Татарстан ГОСБ",
      "GOSB_SHORT_NAME": "ГОСБ",
      "CLUSTER_CODE": "1",
      "GROUPING_CODE": "1",
      "GOSB_CNT": "31",
      "GROUPING_CNT": "31",
      "ORG_UNIT_CODE": "10016633"
    },
    {
      "TB_CODE": "42",
      "TB_FULL_NAME": "Волго-Вятский банк",
      "TB_SHORT_NAME": "ВВБ",
      "GOSB_CODE": "8611",
      "GOSB_NAME": "Владимирское ГОСБ",
      "GOSB_SHORT_NAME": "ГОСБ",
      "CLUSTER_CODE": "3",
      "GROUPING_CODE": "1",
      "GOSB_CNT": "10",
      "GROUPING_CNT": "10",
      "ORG_UNIT_CODE": "10083411"
    },
    {
      "TB_CODE": "42",
      "TB_FULL_NAME": "Волго-Вятский банк",
      "TB_SHORT_NAME": "ВВБ",
      "GOSB_CODE": "8612",
      "GOSB_NAME": "Кировское ГОСБ",
      "GOSB_SHORT_NAME": "ГОСБ",
      "CLUSTER_CODE": "3",
      "GROUPING_CODE": "1",
      "GOSB_CNT": "10",
      "GROUPING_CNT": "10",
      "ORG_UNIT_CODE": "10016640"
    },
    {
      "TB_CODE": "42",
      "TB_FULL_NAME": "Волго-Вятский банк",
      "TB_SHORT_NAME": "ВВБ",
      "GOSB_CODE": "8613",
      "GOSB_NAME": "Чувашское ГОСБ",
      "GOSB_SHORT_NAME": "ГОСБ",
      "CLUSTER_CODE": "4",
      "GROUPING_CODE": "1",
      "GOSB_CNT": "8",
      "GROUPING_CNT": "8",
      "ORG_UNIT_CODE": "10016645"
    },
    {
      "TB_CODE": "42",
      "TB_FULL_NAME": "Волго-Вятский банк",
      "TB_SHORT_NAME": "ВВБ",
      "GOSB_CODE": "8614",
      "GOSB_NAME": "Марий Эл ГОСБ",
      "GOSB_SHORT_NAME": "ГОСБ",
      "CLUSTER_CODE": "5",
      "GROUPING_CODE": "1",
      "GOSB_CNT": "4",
      "GROUPING_CNT": "20",
      "ORG_UNIT_CODE": "10016423"
    },
    {
      "TB_CODE": "42",
      "TB_FULL_NAME": "Волго-Вятский банк",
      "TB_SHORT_NAME": "ВВБ",
      "GOSB_CODE": "8618",
      "GOSB_NAME": "Удмуртское ГОСБ",
      "GOSB_SHORT_NAME": "ГОСБ",
      "CLUSTER_CODE": "2",
      "GROUPING_CODE": "1",
      "GOSB_CNT": "9",
      "GROUPING_CNT": "9",
      "ORG_UNIT_CODE": "10267152"
    },
    {
      "TB_CODE": "42",
      "TB_FULL_NAME": "Волго-Вятский банк",
      "TB_SHORT_NAME": "ВВБ",
      "GOSB_CODE": "9042",
      "GOSB_NAME": "ГО по Нижегородской области",
      "GOSB_SHORT_NAME": "ГОСБ",
      "CLUSTER_CODE": "1",
      "GROUPING_CODE": "1",
      "GOSB_CNT": "30",
      "GROUPING_CNT": "30",
      "ORG_UNIT_CODE": "10039796"
    },
    {
      "TB_CODE": "70",
      "TB_FULL_NAME": "Дальневосточный банк",
      "TB_SHORT_NAME": "ДВБ",
      "GOSB_CODE": "0",
      "GOSB_NAME": "Аппарат территориального банка",
      "GOSB_SHORT_NAME": "Аппарат ДВБ",
      "CLUSTER_CODE": "0",
      "GROUPING_CODE": "1",
      "GOSB_CNT": "0",
      "GROUPING_CNT": "0",
      "ORG_UNIT_CODE": "10016449"
    },
    {
      "TB_CODE": "70",
      "TB_FULL_NAME": "Дальневосточный банк",
      "TB_SHORT_NAME": "ДВБ",
      "GOSB_CODE": "4157",
      "GOSB_NAME": "Биробиджанское ГОСБ",
      "GOSB_SHORT_NAME": "ГОСБ",
      "CLUSTER_CODE": "5",
      "GROUPING_CODE": "1",
      "GOSB_CNT": "1",
      "GROUPING_CNT": "20",
      "ORG_UNIT_CODE": "10038415"
    },
    {
      "TB_CODE": "70",
      "TB_FULL_NAME": "Дальневосточный банк",
      "TB_SHORT_NAME": "ДВБ",
      "GOSB_CODE": "7000",
      "GOSB_NAME": "Аппарат Дальневосточного банка",
      "GOSB_SHORT_NAME": "ЦПКК ДВБ",
      "CLUSTER_CODE": "1",
      "GROUPING_CODE": "1",
      "GOSB_CNT": "8",
      "GROUPING_CNT": "8",
      "ORG_UNIT_CODE": "10296390"
    },
    {
      "TB_CODE": "70",
      "TB_FULL_NAME": "Дальневосточный банк",
      "TB_SHORT_NAME": "ДВБ",
      "GOSB_CODE": "8556",
      "GOSB_NAME": "Камчатское ГОСБ",
      "GOSB_SHORT_NAME": "ГОСБ",
      "CLUSTER_CODE": "4",
      "GROUPING_CODE": "1",
      "GOSB_CNT": "5",
      "GROUPING_CNT": "5",
      "ORG_UNIT_CODE": "10162314"
    },
    {
      "TB_CODE": "70",
      "TB_FULL_NAME": "Дальневосточный банк",
      "TB_SHORT_NAME": "ДВБ",
      "GOSB_CODE": "8557",
      "GOSB_NAME": "Чукотское ГОСБ",
      "GOSB_SHORT_NAME": "ГОСБ",
      "CLUSTER_CODE": "5",
      "GROUPING_CODE": "1",
      "GOSB_CNT": "1",
      "GROUPING_CNT": "20",
      "ORG_UNIT_CODE": "10214308"
    },
    {
      "TB_CODE": "70",
      "TB_FULL_NAME": "Дальневосточный банк",
      "TB_SHORT_NAME": "ДВБ",
      "GOSB_CODE": "8567",
      "GOSB_NAME": "Южно-Сахалинское ГОСБ",
      "GOSB_SHORT_NAME": "ГОСБ",
      "CLUSTER_CODE": "3",
      "GROUPING_CODE": "1",
      "GOSB_CNT": "8",
      "GROUPING_CNT": "8",
      "ORG_UNIT_CODE": "10035960"
    },
    {
      "TB_CODE": "70",
      "TB_FULL_NAME": "Дальневосточный банк",
      "TB_SHORT_NAME": "ДВБ",
      "GOSB_CODE": "8635",
      "GOSB_NAME": "Приморское ГОСБ",
      "GOSB_SHORT_NAME": "ГОСБ",
      "CLUSTER_CODE": "1",
      "GROUPING_CODE": "1",
      "GOSB_CNT": "21",
      "GROUPING_CNT": "21",
      "ORG_UNIT_CODE": "10123013"
    },
    {
      "TB_CODE": "70",
      "TB_FULL_NAME": "Дальневосточный банк",
      "TB_SHORT_NAME": "ДВБ",
      "GOSB_CODE": "8636",
      "GOSB_NAME": "Благовещенское ГОСБ",
      "GOSB_SHORT_NAME": "ГОСБ",
      "CLUSTER_CODE": "3",
      "GROUPING_CODE": "1",
      "GOSB_CNT": "7",
      "GROUPING_CNT": "7",
      "ORG_UNIT_CODE": "10016714"
    },
    {
      "TB_CODE": "70",
      "TB_FULL_NAME": "Дальневосточный банк",
      "TB_SHORT_NAME": "ДВБ",
      "GOSB_CODE": "8645",
      "GOSB_NAME": "Северо-Восточное ГОСБ",
      "GOSB_SHORT_NAME": "ГОСБ",
      "CLUSTER_CODE": "5",
      "GROUPING_CODE": "1",
      "GOSB_CNT": "3",
      "GROUPING_CNT": "20",
      "ORG_UNIT_CODE": "10162311"
    },
    {
      "TB_CODE": "70",
      "TB_FULL_NAME": "Дальневосточный банк",
      "TB_SHORT_NAME": "ДВБ",
      "GOSB_CODE": "9070",
      "GOSB_NAME": "Хабаровское ГОСБ",
      "GOSB_SHORT_NAME": "ГОСБ",
      "CLUSTER_CODE": "2",
      "GROUPING_CODE": "1",
      "GOSB_CNT": "16",
      "GROUPING_CNT": "16",
      "ORG_UNIT_CODE": "10122604"
    },
    {
      "TB_CODE": "38",
      "TB_FULL_NAME": "Московский банк",
      "TB_SHORT_NAME": "МБ",
      "GOSB_CODE": "0",
      "GOSB_NAME": "Аппарат территориального банка",
      "GOSB_SHORT_NAME": "Аппарат МБ",
      "CLUSTER_CODE": "0",
      "GROUPING_CODE": "1",
      "GOSB_CNT": "0",
      "GROUPING_CNT": "0",
      "ORG_UNIT_CODE": "10000367"
    },
    {
      "TB_CODE": "38",
      "TB_FULL_NAME": "Московский банк",
      "TB_SHORT_NAME": "МБ",
      "GOSB_CODE": "9038",
      "GOSB_NAME": "Отделение Московского банка",
      "GOSB_SHORT_NAME": "Аппарат МБ",
      "CLUSTER_CODE": "1",
      "GROUPING_CODE": "1",
      "GOSB_CNT": "0",
      "GROUPING_CNT": "0",
      "ORG_UNIT_CODE": "10156582"
    },
    {
      "TB_CODE": "38",
      "TB_FULL_NAME": "Московский банк",
      "TB_SHORT_NAME": "МБ",
      "GOSB_CODE": "90381",
      "GOSB_NAME": "Управление МБ по работе с предприятиями инфраструктуры",
      "GOSB_SHORT_NAME": "Управление",
      "CLUSTER_CODE": "1",
      "GROUPING_CODE": "1",
      "GOSB_CNT": "22",
      "GROUPING_CNT": "22",
      "ORG_UNIT_CODE": "10242114"
    },
    {
      "TB_CODE": "38",
      "TB_FULL_NAME": "Московский банк",
      "TB_SHORT_NAME": "МБ",
      "GOSB_CODE": "90382",
      "GOSB_NAME": "Управление МБ по работе с предприятиями промышленности",
      "GOSB_SHORT_NAME": "Управление",
      "CLUSTER_CODE": "1",
      "GROUPING_CODE": "1",
      "GOSB_CNT": "33",
      "GROUPING_CNT": "33",
      "ORG_UNIT_CODE": "10242078"
    },
    {
      "TB_CODE": "38",
      "TB_FULL_NAME": "Московский банк",
      "TB_SHORT_NAME": "МБ",
      "GOSB_CODE": "90383",
      "GOSB_NAME": "Управление МБ по работе с предприятиями сферы недвижимости",
      "GOSB_SHORT_NAME": "Управление",
      "CLUSTER_CODE": "1",
      "GROUPING_CODE": "1",
      "GOSB_CNT": "43",
      "GROUPING_CNT": "43",
      "ORG_UNIT_CODE": "10240714"
    },
    {
      "TB_CODE": "38",
      "TB_FULL_NAME": "Московский банк",
      "TB_SHORT_NAME": "МБ",
      "GOSB_CODE": "90384",
      "GOSB_NAME": "Управление МБ по работе с предприятиями сферы услуг",
      "GOSB_SHORT_NAME": "Управление",
      "CLUSTER_CODE": "1",
      "GROUPING_CODE": "1",
      "GOSB_CNT": "29",
      "GROUPING_CNT": "29",
      "ORG_UNIT_CODE": "10241967"
    },
    {
      "TB_CODE": "38",
      "TB_FULL_NAME": "Московский банк",
      "TB_SHORT_NAME": "МБ",
      "GOSB_CODE": "90385",
      "GOSB_NAME": "Управление МБ по работе с предприятиями торговли",
      "GOSB_SHORT_NAME": "Управление",
      "CLUSTER_CODE": "1",
      "GROUPING_CODE": "1",
      "GOSB_CNT": "64",
      "GROUPING_CNT": "64",
      "ORG_UNIT_CODE": "10241463"
    },
    {
      "TB_CODE": "38",
      "TB_FULL_NAME": "Московский банк",
      "TB_SHORT_NAME": "МБ",
      "GOSB_CODE": "90386",
      "GOSB_NAME": "Управление МБ по работе с предприятиями транспорта",
      "GOSB_SHORT_NAME": "Управление",
      "CLUSTER_CODE": "1",
      "GROUPING_CODE": "1",
      "GOSB_CNT": "26",
      "GROUPING_CNT": "26",
      "ORG_UNIT_CODE": "10241962"
    },
    {
      "TB_CODE": "54",
      "TB_FULL_NAME": "Поволжский банк",
      "TB_SHORT_NAME": "ПБ",
      "GOSB_CODE": "0",
      "GOSB_NAME": "Аппарат территориального банка",
      "GOSB_SHORT_NAME": "Аппарат ПБ",
      "CLUSTER_CODE": "0",
      "GROUPING_CODE": "1",
      "GOSB_CNT": "0",
      "GROUPING_CNT": "0",
      "ORG_UNIT_CODE": "10016441"
    },
    {
      "TB_CODE": "54",
      "TB_FULL_NAME": "Поволжский банк",
      "TB_SHORT_NAME": "ПБ",
      "GOSB_CODE": "6991",
      "GOSB_NAME": "Самарское ГОСБ",
      "GOSB_SHORT_NAME": "ГОСБ",
      "CLUSTER_CODE": "1",
      "GROUPING_CODE": "1",
      "GOSB_CNT": "28",
      "GROUPING_CNT": "28",
      "ORG_UNIT_CODE": "10034502"
    },
    {
      "TB_CODE": "54",
      "TB_FULL_NAME": "Поволжский банк",
      "TB_SHORT_NAME": "ПБ",
      "GOSB_CODE": "8588",
      "GOSB_NAME": "Ульяновское ГОСБ",
      "GOSB_SHORT_NAME": "ГОСБ",
      "CLUSTER_CODE": "3",
      "GROUPING_CODE": "1",
      "GOSB_CNT": "8",
      "GROUPING_CNT": "8",
      "ORG_UNIT_CODE": "10016636"
    },
    {
      "TB_CODE": "54",
      "TB_FULL_NAME": "Поволжский банк",
      "TB_SHORT_NAME": "ПБ",
      "GOSB_CODE": "8621",
      "GOSB_NAME": "Волгоградское ГОСБ",
      "GOSB_SHORT_NAME": "ГОСБ",
      "CLUSTER_CODE": "2",
      "GROUPING_CODE": "1",
      "GOSB_CNT": "18",
      "GROUPING_CNT": "18",
      "ORG_UNIT_CODE": "10016651"
    },
    {
      "TB_CODE": "54",
      "TB_FULL_NAME": "Поволжский банк",
      "TB_SHORT_NAME": "ПБ",
      "GOSB_CODE": "8622",
      "GOSB_NAME": "Саратовское ГОСБ",
      "GOSB_SHORT_NAME": "ГОСБ",
      "CLUSTER_CODE": "2",
      "GROUPING_CODE": "1",
      "GOSB_CNT": "17",
      "GROUPING_CNT": "17",
      "ORG_UNIT_CODE": "10016652"
    },
    {
      "TB_CODE": "54",
      "TB_FULL_NAME": "Поволжский банк",
      "TB_SHORT_NAME": "ПБ",
      "GOSB_CODE": "8623",
      "GOSB_NAME": "Оренбургское ГОСБ",
      "GOSB_SHORT_NAME": "ГОСБ",
      "CLUSTER_CODE": "2",
      "GROUPING_CODE": "1",
      "GOSB_CNT": "12",
      "GROUPING_CNT": "12",
      "ORG_UNIT_CODE": "10016642"
    },
    {
      "TB_CODE": "54",
      "TB_FULL_NAME": "Поволжский банк",
      "TB_SHORT_NAME": "ПБ",
      "GOSB_CODE": "8624",
      "GOSB_NAME": "Пензенское ГОСБ",
      "GOSB_SHORT_NAME": "ГОСБ",
      "CLUSTER_CODE": "3",
      "GROUPING_CODE": "1",
      "GOSB_CNT": "10",
      "GROUPING_CNT": "10",
      "ORG_UNIT_CODE": "10016639"
    },
    {
      "TB_CODE": "54",
      "TB_FULL_NAME": "Поволжский банк",
      "TB_SHORT_NAME": "ПБ",
      "GOSB_CODE": "8625",
      "GOSB_NAME": "Астраханское ГОСБ",
      "GOSB_SHORT_NAME": "ГОСБ",
      "CLUSTER_CODE": "4",
      "GROUPING_CODE": "1",
      "GOSB_CNT": "6",
      "GROUPING_CNT": "6",
      "ORG_UNIT_CODE": "10033835"
    },
    {
      "TB_CODE": "54",
      "TB_FULL_NAME": "Поволжский банк",
      "TB_SHORT_NAME": "ПБ",
      "GOSB_CODE": "9054",
      "GOSB_NAME": "Аппарат Поволжского банка",
      "GOSB_SHORT_NAME": "ЦПКК ПБ",
      "CLUSTER_CODE": "1",
      "GROUPING_CODE": "1",
      "GOSB_CNT": "9",
      "GROUPING_CNT": "9",
      "ORG_UNIT_CODE": "10295424"
    },
    {
      "TB_CODE": "999",
      "TB_FULL_NAME": "Сбербанк",
      "TB_SHORT_NAME": "Сбер",
      "GOSB_CODE": "0",
      "GOSB_NAME": "",
      "GOSB_SHORT_NAME": "Сбер",
      "CLUSTER_CODE": "0",
      "GROUPING_CODE": "1",
      "GOSB_CNT": "0",
      "GROUPING_CNT": "0",
      "ORG_UNIT_CODE": "10000001"
    },
    {
      "TB_CODE": "100",
      "TB_FULL_NAME": "Сбербанк",
      "TB_SHORT_NAME": "Сбер",
      "GOSB_CODE": "0",
      "GOSB_NAME": "",
      "GOSB_SHORT_NAME": "Сбер",
      "CLUSTER_CODE": "0",
      "GROUPING_CODE": "1",
      "GOSB_CNT": "0",
      "GROUPING_CNT": "0",
      "ORG_UNIT_CODE": "10000002"
    },
    {
      "TB_CODE": "101",
      "TB_FULL_NAME": "Сбер Факторинг",
      "TB_SHORT_NAME": "Сбер Факторинг",
      "GOSB_CODE": "0",
      "GOSB_NAME": "",
      "GOSB_SHORT_NAME": "Подразделение",
      "CLUSTER_CODE": "0",
      "GROUPING_CODE": "1",
      "GOSB_CNT": "0",
      "GROUPING_CNT": "0",
      "ORG_UNIT_CODE": "110000001"
    },
    {
      "TB_CODE": "102",
      "TB_FULL_NAME": "Сбербанк Лизинг",
      "TB_SHORT_NAME": "Сбербанк Лизинг",
      "GOSB_CODE": "0",
      "GOSB_NAME": "",
      "GOSB_SHORT_NAME": "Подразделение",
      "CLUSTER_CODE": "0",
      "GROUPING_CODE": "1",
      "GOSB_CNT": "0",
      "GROUPING_CNT": "0",
      "ORG_UNIT_CODE": "800004668"
    },
    {
      "TB_CODE": "103",
      "TB_FULL_NAME": "Подразделения центрального подчинения",
      "TB_SHORT_NAME": "ПЦП",
      "GOSB_CODE": "0",
      "GOSB_NAME": "",
      "GOSB_SHORT_NAME": "ПЦП",
      "CLUSTER_CODE": "0",
      "GROUPING_CODE": "1",
      "GOSB_CNT": "0",
      "GROUPING_CNT": "0",
      "ORG_UNIT_CODE": "10110907"
    },
    {
      "TB_CODE": "104",
      "TB_FULL_NAME": "ДЗО",
      "TB_SHORT_NAME": "ДЗО",
      "GOSB_CODE": "0",
      "GOSB_NAME": "",
      "GOSB_SHORT_NAME": "ДЗО",
      "CLUSTER_CODE": "0",
      "GROUPING_CODE": "1",
      "GOSB_CNT": "0",
      "GROUPING_CNT": "0",
      "ORG_UNIT_CODE": "999000001"
    },
    {
      "TB_CODE": "105",
      "TB_FULL_NAME": "Экосистема",
      "TB_SHORT_NAME": "Экосистема",
      "GOSB_CODE": "0",
      "GOSB_NAME": "",
      "GOSB_SHORT_NAME": "Подразделение",
      "CLUSTER_CODE": "0",
      "GROUPING_CODE": "1",
      "GOSB_CNT": "0",
      "GROUPING_CNT": "0",
      "ORG_UNIT_CODE": "999000000"
    },
    {
      "TB_CODE": "106",
      "TB_FULL_NAME": "Подрядные организации",
      "TB_SHORT_NAME": "ШД",
      "GOSB_CODE": "0",
      "GOSB_NAME": "",
      "GOSB_SHORT_NAME": "Подразделение",
      "CLUSTER_CODE": "0",
      "GROUPING_CODE": "1",
      "GOSB_CNT": "0",
      "GROUPING_CNT": "0",
      "ORG_UNIT_CODE": "10283183"
    },
    {
      "TB_CODE": "107",
      "TB_FULL_NAME": "Филиал ПАО Сбербанк в Индии",
      "TB_SHORT_NAME": "Сбербанк в Индии",
      "GOSB_CODE": "0",
      "GOSB_NAME": "",
      "GOSB_SHORT_NAME": "Подразделение",
      "CLUSTER_CODE": "0",
      "GROUPING_CODE": "1",
      "GOSB_CNT": "0",
      "GROUPING_CNT": "0",
      "ORG_UNIT_CODE": "1300000000"
    },
    {
      "TB_CODE": "108",
      "TB_FULL_NAME": "Дочерние Банки",
      "TB_SHORT_NAME": "Дочерние Банки",
      "GOSB_CODE": "0",
      "GOSB_NAME": "",
      "GOSB_SHORT_NAME": "Подразделение",
      "CLUSTER_CODE": "0",
      "GROUPING_CODE": "1",
      "GOSB_CNT": "0",
      "GROUPING_CNT": "0",
      "ORG_UNIT_CODE": "600000000"
    },
    {
      "TB_CODE": "55",
      "TB_FULL_NAME": "Северо-Западный банк",
      "TB_SHORT_NAME": "СЗБ",
      "GOSB_CODE": "0",
      "GOSB_NAME": "Аппарат территориального банка",
      "GOSB_SHORT_NAME": "Аппарат СЗБ",
      "CLUSTER_CODE": "0",
      "GROUPING_CODE": "1",
      "GOSB_CNT": "0",
      "GROUPING_CNT": "0",
      "ORG_UNIT_CODE": "10086568"
    },
    {
      "TB_CODE": "55",
      "TB_FULL_NAME": "Северо-Западный банк",
      "TB_SHORT_NAME": "СЗБ",
      "GOSB_CODE": "8617",
      "GOSB_NAME": "Коми ГОСБ",
      "GOSB_SHORT_NAME": "ГОСБ",
      "CLUSTER_CODE": "3",
      "GROUPING_CODE": "1",
      "GOSB_CNT": "7",
      "GROUPING_CNT": "7",
      "ORG_UNIT_CODE": "10264012"
    },
    {
      "TB_CODE": "55",
      "TB_FULL_NAME": "Северо-Западный банк",
      "TB_SHORT_NAME": "СЗБ",
      "GOSB_CODE": "8626",
      "GOSB_NAME": "Калининградское ГОСБ",
      "GOSB_SHORT_NAME": "ГОСБ",
      "CLUSTER_CODE": "3",
      "GROUPING_CODE": "1",
      "GOSB_CNT": "10",
      "GROUPING_CNT": "10",
      "ORG_UNIT_CODE": "10086543"
    },
    {
      "TB_CODE": "55",
      "TB_FULL_NAME": "Северо-Западный банк",
      "TB_SHORT_NAME": "СЗБ",
      "GOSB_CODE": "8627",
      "GOSB_NAME": "Мурманское ГОСБ",
      "GOSB_SHORT_NAME": "ГОСБ",
      "CLUSTER_CODE": "2",
      "GROUPING_CODE": "1",
      "GOSB_CNT": "5",
      "GROUPING_CNT": "5",
      "ORG_UNIT_CODE": "10099906"
    },
    {
      "TB_CODE": "55",
      "TB_FULL_NAME": "Северо-Западный банк",
      "TB_SHORT_NAME": "СЗБ",
      "GOSB_CODE": "8628",
      "GOSB_NAME": "Карельское ГОСБ",
      "GOSB_SHORT_NAME": "ГОСБ",
      "CLUSTER_CODE": "4",
      "GROUPING_CODE": "1",
      "GOSB_CNT": "10",
      "GROUPING_CNT": "10",
      "ORG_UNIT_CODE": "10086650"
    },
    {
      "TB_CODE": "55",
      "TB_FULL_NAME": "Северо-Западный банк",
      "TB_SHORT_NAME": "СЗБ",
      "GOSB_CODE": "8629",
      "GOSB_NAME": "Новгородское ГОСБ",
      "GOSB_SHORT_NAME": "ГОСБ",
      "CLUSTER_CODE": "4",
      "GROUPING_CODE": "1",
      "GOSB_CNT": "4",
      "GROUPING_CNT": "4",
      "ORG_UNIT_CODE": "10086651"
    },
    {
      "TB_CODE": "55",
      "TB_FULL_NAME": "Северо-Западный банк",
      "TB_SHORT_NAME": "СЗБ",
      "GOSB_CODE": "8630",
      "GOSB_NAME": "Псковское ГОСБ",
      "GOSB_SHORT_NAME": "ГОСБ",
      "CLUSTER_CODE": "4",
      "GROUPING_CODE": "1",
      "GOSB_CNT": "5",
      "GROUPING_CNT": "5",
      "ORG_UNIT_CODE": "10086652"
    },
    {
      "TB_CODE": "55",
      "TB_FULL_NAME": "Северо-Западный банк",
      "TB_SHORT_NAME": "СЗБ",
      "GOSB_CODE": "8637",
      "GOSB_NAME": "Архангельское ГОСБ",
      "GOSB_SHORT_NAME": "ГОСБ",
      "CLUSTER_CODE": "2",
      "GROUPING_CODE": "1",
      "GOSB_CNT": "8",
      "GROUPING_CNT": "8",
      "ORG_UNIT_CODE": "10263275"
    },
    {
      "TB_CODE": "55",
      "TB_FULL_NAME": "Северо-Западный банк",
      "TB_SHORT_NAME": "СЗБ",
      "GOSB_CODE": "8638",
      "GOSB_NAME": "Вологодское ГОСБ",
      "GOSB_SHORT_NAME": "ГОСБ",
      "CLUSTER_CODE": "3",
      "GROUPING_CODE": "1",
      "GOSB_CNT": "15",
      "GROUPING_CNT": "15",
      "ORG_UNIT_CODE": "10263631"
    },
    {
      "TB_CODE": "55",
      "TB_FULL_NAME": "Северо-Западный банк",
      "TB_SHORT_NAME": "СЗБ",
      "GOSB_CODE": "9055",
      "GOSB_NAME": "Аппарат Северо-Западного банка",
      "GOSB_SHORT_NAME": "ЦПКК СЗБ",
      "CLUSTER_CODE": "1",
      "GROUPING_CODE": "1",
      "GOSB_CNT": "18",
      "GROUPING_CNT": "18",
      "ORG_UNIT_CODE": "10298976"
    },
    {
      "TB_CODE": "55",
      "TB_FULL_NAME": "Северо-Западный банк",
      "TB_SHORT_NAME": "СЗБ",
      "GOSB_CODE": "9500",
      "GOSB_NAME": "ГО по Санкт-Петербургу",
      "GOSB_SHORT_NAME": "ГОСБ",
      "CLUSTER_CODE": "1",
      "GROUPING_CODE": "1",
      "GOSB_CNT": "78",
      "GROUPING_CNT": "78",
      "ORG_UNIT_CODE": "10086553"
    },
    {
      "TB_CODE": "55",
      "TB_FULL_NAME": "Северо-Западный банк",
      "TB_SHORT_NAME": "СЗБ",
      "GOSB_CODE": "9600",
      "GOSB_NAME": "ГО по Ленинградской области",
      "GOSB_SHORT_NAME": "ГОСБ",
      "CLUSTER_CODE": "2",
      "GROUPING_CODE": "1",
      "GOSB_CNT": "17",
      "GROUPING_CNT": "17",
      "ORG_UNIT_CODE": "10086573"
    },
    {
      "TB_CODE": "44",
      "TB_FULL_NAME": "Сибирский банк",
      "TB_SHORT_NAME": "СИБ",
      "GOSB_CODE": "0",
      "GOSB_NAME": "Аппарат территориального банка",
      "GOSB_SHORT_NAME": "Аппарат СИБ",
      "CLUSTER_CODE": "0",
      "GROUPING_CODE": "1",
      "GOSB_CNT": "0",
      "GROUPING_CNT": "0",
      "ORG_UNIT_CODE": "10108866"
    },
    {
      "TB_CODE": "44",
      "TB_FULL_NAME": "Сибирский банк",
      "TB_SHORT_NAME": "СИБ",
      "GOSB_CODE": "8047",
      "GOSB_NAME": "Новосибирское ГОСБ",
      "GOSB_SHORT_NAME": "ГОСБ",
      "CLUSTER_CODE": "1",
      "GROUPING_CODE": "1",
      "GOSB_CNT": "28",
      "GROUPING_CNT": "28",
      "ORG_UNIT_CODE": "10038836"
    },
    {
      "TB_CODE": "44",
      "TB_FULL_NAME": "Сибирский банк",
      "TB_SHORT_NAME": "СИБ",
      "GOSB_CODE": "8558",
      "GOSB_NAME": "Горно-Алтайское ГОСБ",
      "GOSB_SHORT_NAME": "ГОСБ",
      "CLUSTER_CODE": "5",
      "GROUPING_CODE": "1",
      "GOSB_CNT": "0",
      "GROUPING_CNT": "0",
      "ORG_UNIT_CODE": "10038927"
    },
    {
      "TB_CODE": "44",
      "TB_FULL_NAME": "Сибирский банк",
      "TB_SHORT_NAME": "СИБ",
      "GOSB_CODE": "8591",
      "GOSB_NAME": "Кызылское ГОСБ",
      "GOSB_SHORT_NAME": "ГОСБ",
      "CLUSTER_CODE": "5",
      "GROUPING_CODE": "1",
      "GOSB_CNT": "0",
      "GROUPING_CNT": "0",
      "ORG_UNIT_CODE": "10199741"
    },
    {
      "TB_CODE": "44",
      "TB_FULL_NAME": "Сибирский банк",
      "TB_SHORT_NAME": "СИБ",
      "GOSB_CODE": "8602",
      "GOSB_NAME": "Абаканское ГОСБ",
      "GOSB_SHORT_NAME": "ГОСБ",
      "CLUSTER_CODE": "5",
      "GROUPING_CODE": "1",
      "GOSB_CNT": "0",
      "GROUPING_CNT": "0",
      "ORG_UNIT_CODE": "10199468"
    },
    {
      "TB_CODE": "44",
      "TB_FULL_NAME": "Сибирский банк",
      "TB_SHORT_NAME": "СИБ",
      "GOSB_CODE": "8615",
      "GOSB_NAME": "Кемеровское ГОСБ",
      "GOSB_SHORT_NAME": "ГОСБ",
      "CLUSTER_CODE": "1",
      "GROUPING_CODE": "1",
      "GOSB_CNT": "17",
      "GROUPING_CNT": "17",
      "ORG_UNIT_CODE": "10016700"
    },
    {
      "TB_CODE": "44",
      "TB_FULL_NAME": "Сибирский банк",
      "TB_SHORT_NAME": "СИБ",
      "GOSB_CODE": "8616",
      "GOSB_NAME": "Томское ГОСБ",
      "GOSB_SHORT_NAME": "ГОСБ",
      "CLUSTER_CODE": "4",
      "GROUPING_CODE": "1",
      "GOSB_CNT": "8",
      "GROUPING_CNT": "8",
      "ORG_UNIT_CODE": "10016701"
    },
    {
      "TB_CODE": "44",
      "TB_FULL_NAME": "Сибирский банк",
      "TB_SHORT_NAME": "СИБ",
      "GOSB_CODE": "8634",
      "GOSB_NAME": "Омское ГОСБ",
      "GOSB_SHORT_NAME": "ГОСБ",
      "CLUSTER_CODE": "2",
      "GROUPING_CODE": "1",
      "GOSB_CNT": "11",
      "GROUPING_CNT": "11",
      "ORG_UNIT_CODE": "10297137"
    },
    {
      "TB_CODE": "44",
      "TB_FULL_NAME": "Сибирский банк",
      "TB_SHORT_NAME": "СИБ",
      "GOSB_CODE": "8644",
      "GOSB_NAME": "Алтайское ГОСБ",
      "GOSB_SHORT_NAME": "ГОСБ",
      "CLUSTER_CODE": "2",
      "GROUPING_CODE": "1",
      "GOSB_CNT": "14",
      "GROUPING_CNT": "14",
      "ORG_UNIT_CODE": "10038642"
    },
    {
      "TB_CODE": "44",
      "TB_FULL_NAME": "Сибирский банк",
      "TB_SHORT_NAME": "СИБ",
      "GOSB_CODE": "8646",
      "GOSB_NAME": "Красноярское ГОСБ",
      "GOSB_SHORT_NAME": "ГОСБ",
      "CLUSTER_CODE": "1",
      "GROUPING_CODE": "1",
      "GOSB_CNT": "30",
      "GROUPING_CNT": "30",
      "ORG_UNIT_CODE": "10198065"
    },
    {
      "TB_CODE": "44",
      "TB_FULL_NAME": "Сибирский банк",
      "TB_SHORT_NAME": "СИБ",
      "GOSB_CODE": "9044",
      "GOSB_NAME": "Аппарат Сибирского банка",
      "GOSB_SHORT_NAME": "ЦПКК СИБ",
      "CLUSTER_CODE": "1",
      "GROUPING_CODE": "1",
      "GOSB_CNT": "13",
      "GROUPING_CNT": "13",
      "ORG_UNIT_CODE": "10295911"
    },
    {
      "TB_CODE": "40",
      "TB_FULL_NAME": "Среднерусский банк",
      "TB_SHORT_NAME": "СРБ",
      "GOSB_CODE": "0",
      "GOSB_NAME": "Аппарат территориального банка",
      "GOSB_SHORT_NAME": "Аппарат СРБ",
      "CLUSTER_CODE": "0",
      "GROUPING_CODE": "1",
      "GOSB_CNT": "0",
      "GROUPING_CNT": "0",
      "ORG_UNIT_CODE": "10016443"
    },
    {
      "TB_CODE": "40",
      "TB_FULL_NAME": "Среднерусский банк",
      "TB_SHORT_NAME": "СРБ",
      "GOSB_CODE": "17",
      "GOSB_NAME": "Ярославское ГОСБ",
      "GOSB_SHORT_NAME": "ГОСБ",
      "CLUSTER_CODE": "2",
      "GROUPING_CODE": "1",
      "GOSB_CNT": "10",
      "GROUPING_CNT": "10",
      "ORG_UNIT_CODE": "10265572"
    },
    {
      "TB_CODE": "40",
      "TB_FULL_NAME": "Среднерусский банк",
      "TB_SHORT_NAME": "СРБ",
      "GOSB_CODE": "1023",
      "GOSB_NAME": "Восточное ГОСБ",
      "GOSB_SHORT_NAME": "ГОСБ",
      "CLUSTER_CODE": "1",
      "GROUPING_CODE": "1",
      "GOSB_CNT": "22",
      "GROUPING_CNT": "22",
      "ORG_UNIT_CODE": "10182580"
    },
    {
      "TB_CODE": "40",
      "TB_FULL_NAME": "Среднерусский банк",
      "TB_SHORT_NAME": "СРБ",
      "GOSB_CODE": "1024",
      "GOSB_NAME": "Южное ГОСБ",
      "GOSB_SHORT_NAME": "ГОСБ",
      "CLUSTER_CODE": "1",
      "GROUPING_CODE": "1",
      "GOSB_CNT": "24",
      "GROUPING_CNT": "24",
      "ORG_UNIT_CODE": "10182581"
    },
    {
      "TB_CODE": "40",
      "TB_FULL_NAME": "Среднерусский банк",
      "TB_SHORT_NAME": "СРБ",
      "GOSB_CODE": "1025",
      "GOSB_NAME": "Западное ГОСБ",
      "GOSB_SHORT_NAME": "ГОСБ",
      "CLUSTER_CODE": "1",
      "GROUPING_CODE": "1",
      "GOSB_CNT": "29",
      "GROUPING_CNT": "29",
      "ORG_UNIT_CODE": "10182582"
    },
    {
      "TB_CODE": "40",
      "TB_FULL_NAME": "Среднерусский банк",
      "TB_SHORT_NAME": "СРБ",
      "GOSB_CODE": "1026",
      "GOSB_NAME": "Северное ГОСБ",
      "GOSB_SHORT_NAME": "ГОСБ",
      "CLUSTER_CODE": "1",
      "GROUPING_CODE": "1",
      "GOSB_CNT": "24",
      "GROUPING_CNT": "24",
      "ORG_UNIT_CODE": "10182583"
    },
    {
      "TB_CODE": "40",
      "TB_FULL_NAME": "Среднерусский банк",
      "TB_SHORT_NAME": "СРБ",
      "GOSB_CODE": "3000",
      "GOSB_NAME": "Аппарат Среднерусского банка",
      "GOSB_SHORT_NAME": "ЦПКК СРБ",
      "CLUSTER_CODE": "1",
      "GROUPING_CODE": "1",
      "GOSB_CNT": "18",
      "GROUPING_CNT": "18",
      "ORG_UNIT_CODE": "10290247"
    },
    {
      "TB_CODE": "40",
      "TB_FULL_NAME": "Среднерусский банк",
      "TB_SHORT_NAME": "СРБ",
      "GOSB_CODE": "8604",
      "GOSB_NAME": "Тульское ГОСБ",
      "GOSB_SHORT_NAME": "ГОСБ",
      "CLUSTER_CODE": "2",
      "GROUPING_CODE": "1",
      "GOSB_CNT": "15",
      "GROUPING_CNT": "15",
      "ORG_UNIT_CODE": "10016650"
    },
    {
      "TB_CODE": "40",
      "TB_FULL_NAME": "Среднерусский банк",
      "TB_SHORT_NAME": "СРБ",
      "GOSB_CODE": "8605",
      "GOSB_NAME": "Брянское ГОСБ",
      "GOSB_SHORT_NAME": "ГОСБ",
      "CLUSTER_CODE": "4",
      "GROUPING_CODE": "1",
      "GOSB_CNT": "9",
      "GROUPING_CNT": "9",
      "ORG_UNIT_CODE": "10016647"
    },
    {
      "TB_CODE": "40",
      "TB_FULL_NAME": "Среднерусский банк",
      "TB_SHORT_NAME": "СРБ",
      "GOSB_CODE": "8606",
      "GOSB_NAME": "Рязанское ГОСБ",
      "GOSB_SHORT_NAME": "ГОСБ",
      "CLUSTER_CODE": "3",
      "GROUPING_CODE": "1",
      "GOSB_CNT": "10",
      "GROUPING_CNT": "10",
      "ORG_UNIT_CODE": "10016648"
    },
    {
      "TB_CODE": "40",
      "TB_FULL_NAME": "Среднерусский банк",
      "TB_SHORT_NAME": "СРБ",
      "GOSB_CODE": "8607",
      "GOSB_NAME": "Тверское ГОСБ",
      "GOSB_SHORT_NAME": "ГОСБ",
      "CLUSTER_CODE": "3",
      "GROUPING_CODE": "1",
      "GOSB_CNT": "8",
      "GROUPING_CNT": "8",
      "ORG_UNIT_CODE": "10016671"
    },
    {
      "TB_CODE": "40",
      "TB_FULL_NAME": "Среднерусский банк",
      "TB_SHORT_NAME": "СРБ",
      "GOSB_CODE": "8608",
      "GOSB_NAME": "Калужское ГОСБ",
      "GOSB_SHORT_NAME": "ГОСБ",
      "CLUSTER_CODE": "3",
      "GROUPING_CODE": "1",
      "GOSB_CNT": "12",
      "GROUPING_CNT": "12",
      "ORG_UNIT_CODE": "10016629"
    },
    {
      "TB_CODE": "40",
      "TB_FULL_NAME": "Среднерусский банк",
      "TB_SHORT_NAME": "СРБ",
      "GOSB_CODE": "8609",
      "GOSB_NAME": "Смоленское ГОСБ",
      "GOSB_SHORT_NAME": "ГОСБ",
      "CLUSTER_CODE": "4",
      "GROUPING_CODE": "1",
      "GOSB_CNT": "10",
      "GROUPING_CNT": "10",
      "ORG_UNIT_CODE": "10016649"
    },
    {
      "TB_CODE": "40",
      "TB_FULL_NAME": "Среднерусский банк",
      "TB_SHORT_NAME": "СРБ",
      "GOSB_CODE": "8639",
      "GOSB_NAME": "Ивановское ГОСБ",
      "GOSB_SHORT_NAME": "ГОСБ",
      "CLUSTER_CODE": "4",
      "GROUPING_CODE": "1",
      "GOSB_CNT": "10",
      "GROUPING_CNT": "10",
      "ORG_UNIT_CODE": "10265346"
    },
    {
      "TB_CODE": "40",
      "TB_FULL_NAME": "Среднерусский банк",
      "TB_SHORT_NAME": "СРБ",
      "GOSB_CODE": "8640",
      "GOSB_NAME": "Костромское ГОСБ",
      "GOSB_SHORT_NAME": "ГОСБ",
      "CLUSTER_CODE": "4",
      "GROUPING_CODE": "1",
      "GOSB_CNT": "6",
      "GROUPING_CNT": "6",
      "ORG_UNIT_CODE": "10265143"
    },
    {
      "TB_CODE": "40",
      "TB_FULL_NAME": "Среднерусский банк",
      "TB_SHORT_NAME": "СРБ",
      "GOSB_CODE": "9040",
      "GOSB_NAME": "Отделение Среднерусского банка",
      "GOSB_SHORT_NAME": "Аппарат СРБ",
      "CLUSTER_CODE": "1",
      "GROUPING_CODE": "1",
      "GOSB_CNT": "0",
      "GROUPING_CNT": "0",
      "ORG_UNIT_CODE": "10300825"
    },
    {
      "TB_CODE": "16",
      "TB_FULL_NAME": "Уральский банк",
      "TB_SHORT_NAME": "УБ",
      "GOSB_CODE": "0",
      "GOSB_NAME": "Аппарат территориального банка",
      "GOSB_SHORT_NAME": "Аппарат УБ",
      "CLUSTER_CODE": "0",
      "GROUPING_CODE": "1",
      "GOSB_CNT": "0",
      "GROUPING_CNT": "0",
      "ORG_UNIT_CODE": "10016445"
    },
    {
      "TB_CODE": "16",
      "TB_FULL_NAME": "Уральский банк",
      "TB_SHORT_NAME": "УБ",
      "GOSB_CODE": "5940",
      "GOSB_NAME": "Югорское отделение",
      "GOSB_SHORT_NAME": "ГОСБ",
      "CLUSTER_CODE": "1",
      "GROUPING_CODE": "1",
      "GOSB_CNT": "16",
      "GROUPING_CNT": "16",
      "ORG_UNIT_CODE": "10297711"
    },
    {
      "TB_CODE": "16",
      "TB_FULL_NAME": "Уральский банк",
      "TB_SHORT_NAME": "УБ",
      "GOSB_CODE": "7003",
      "GOSB_NAME": "Свердловское ГОСБ",
      "GOSB_SHORT_NAME": "ГОСБ",
      "CLUSTER_CODE": "1",
      "GROUPING_CODE": "1",
      "GOSB_CNT": "43",
      "GROUPING_CNT": "43",
      "ORG_UNIT_CODE": "10087096"
    },
    {
      "TB_CODE": "16",
      "TB_FULL_NAME": "Уральский банк",
      "TB_SHORT_NAME": "УБ",
      "GOSB_CODE": "8369",
      "GOSB_NAME": "Ямало-Ненецкое отделение",
      "GOSB_SHORT_NAME": "ГОСБ",
      "CLUSTER_CODE": "3",
      "GROUPING_CODE": "1",
      "GOSB_CNT": "4",
      "GROUPING_CNT": "4",
      "ORG_UNIT_CODE": "10297513"
    },
    {
      "TB_CODE": "16",
      "TB_FULL_NAME": "Уральский банк",
      "TB_SHORT_NAME": "УБ",
      "GOSB_CODE": "8597",
      "GOSB_NAME": "Челябинское ГОСБ",
      "GOSB_SHORT_NAME": "ГОСБ",
      "CLUSTER_CODE": "1",
      "GROUPING_CODE": "1",
      "GOSB_CNT": "23",
      "GROUPING_CNT": "23",
      "ORG_UNIT_CODE": "10016641"
    },
    {
      "TB_CODE": "16",
      "TB_FULL_NAME": "Уральский банк",
      "TB_SHORT_NAME": "УБ",
      "GOSB_CODE": "8598",
      "GOSB_NAME": "Башкирское ГОСБ",
      "GOSB_SHORT_NAME": "ГОСБ",
      "CLUSTER_CODE": "1",
      "GROUPING_CODE": "1",
      "GOSB_CNT": "21",
      "GROUPING_CNT": "21",
      "ORG_UNIT_CODE": "10016718"
    },
    {
      "TB_CODE": "16",
      "TB_FULL_NAME": "Уральский банк",
      "TB_SHORT_NAME": "УБ",
      "GOSB_CODE": "8599",
      "GOSB_NAME": "Курганское ГОСБ",
      "GOSB_SHORT_NAME": "ГОСБ",
      "CLUSTER_CODE": "4",
      "GROUPING_CODE": "1",
      "GOSB_CNT": "5",
      "GROUPING_CNT": "5",
      "ORG_UNIT_CODE": "10016723"
    },
    {
      "TB_CODE": "16",
      "TB_FULL_NAME": "Уральский банк",
      "TB_SHORT_NAME": "УБ",
      "GOSB_CODE": "8647",
      "GOSB_NAME": "Западно-Сибирское ГОСБ",
      "GOSB_SHORT_NAME": "ГОСБ",
      "CLUSTER_CODE": "2",
      "GROUPING_CODE": "1",
      "GOSB_CNT": "19",
      "GROUPING_CNT": "19",
      "ORG_UNIT_CODE": "10295881"
    },
    {
      "TB_CODE": "16",
      "TB_FULL_NAME": "Уральский банк",
      "TB_SHORT_NAME": "УБ",
      "GOSB_CODE": "9016",
      "GOSB_NAME": "Аппарат Уральского банка",
      "GOSB_SHORT_NAME": "ЦПКК УБ",
      "CLUSTER_CODE": "1",
      "GROUPING_CODE": "1",
      "GOSB_CNT": "24",
      "GROUPING_CNT": "24",
      "ORG_UNIT_CODE": "10293489"
    },
    {
      "TB_CODE": "99",
      "TB_FULL_NAME": "Центральный аппарат",
      "TB_SHORT_NAME": "ЦА",
      "GOSB_CODE": "0",
      "GOSB_NAME": "",
      "GOSB_SHORT_NAME": "ЦА",
      "CLUSTER_CODE": "0",
      "GROUPING_CODE": "1",
      "GOSB_CNT": "0",
      "GROUPING_CNT": "0",
      "ORG_UNIT_CODE": "10000360"
    },
    {
      "TB_CODE": "13",
      "TB_FULL_NAME": "Центрально-Черноземный банк",
      "TB_SHORT_NAME": "ЦЧБ",
      "GOSB_CODE": "0",
      "GOSB_NAME": "Аппарат территориального банка",
      "GOSB_SHORT_NAME": "Аппарат ЦЧБ",
      "CLUSTER_CODE": "0",
      "GROUPING_CODE": "1",
      "GOSB_CNT": "0",
      "GROUPING_CNT": "0",
      "ORG_UNIT_CODE": "10016678"
    },
    {
      "TB_CODE": "13",
      "TB_FULL_NAME": "Центрально-Черноземный банк",
      "TB_SHORT_NAME": "ЦЧБ",
      "GOSB_CODE": "1300",
      "GOSB_NAME": "Аппарат Центрально-Черноземного банка",
      "GOSB_SHORT_NAME": "ЦПКК ЦЧБ",
      "CLUSTER_CODE": "1",
      "GROUPING_CODE": "1",
      "GOSB_CNT": "12",
      "GROUPING_CNT": "12",
      "ORG_UNIT_CODE": "10293924"
    },
    {
      "TB_CODE": "13",
      "TB_FULL_NAME": "Центрально-Черноземный банк",
      "TB_SHORT_NAME": "ЦЧБ",
      "GOSB_CODE": "8592",
      "GOSB_NAME": "Белгородское ГОСБ",
      "GOSB_SHORT_NAME": "ГОСБ",
      "CLUSTER_CODE": "2",
      "GROUPING_CODE": "1",
      "GOSB_CNT": "21",
      "GROUPING_CNT": "21",
      "ORG_UNIT_CODE": "10016696"
    },
    {
      "TB_CODE": "13",
      "TB_FULL_NAME": "Центрально-Черноземный банк",
      "TB_SHORT_NAME": "ЦЧБ",
      "GOSB_CODE": "8593",
      "GOSB_NAME": "Липецкое ГОСБ",
      "GOSB_SHORT_NAME": "ГОСБ",
      "CLUSTER_CODE": "3",
      "GROUPING_CODE": "1",
      "GOSB_CNT": "10",
      "GROUPING_CNT": "10",
      "ORG_UNIT_CODE": "10016695"
    },
    {
      "TB_CODE": "13",
      "TB_FULL_NAME": "Центрально-Черноземный банк",
      "TB_SHORT_NAME": "ЦЧБ",
      "GOSB_CODE": "8594",
      "GOSB_NAME": "Тамбовское ГОСБ",
      "GOSB_SHORT_NAME": "ГОСБ",
      "CLUSTER_CODE": "4",
      "GROUPING_CODE": "1",
      "GOSB_CNT": "8",
      "GROUPING_CNT": "8",
      "ORG_UNIT_CODE": "10016698"
    },
    {
      "TB_CODE": "13",
      "TB_FULL_NAME": "Центрально-Черноземный банк",
      "TB_SHORT_NAME": "ЦЧБ",
      "GOSB_CODE": "8595",
      "GOSB_NAME": "Орловское ГОСБ",
      "GOSB_SHORT_NAME": "ГОСБ",
      "CLUSTER_CODE": "4",
      "GROUPING_CODE": "1",
      "GOSB_CNT": "7",
      "GROUPING_CNT": "7",
      "ORG_UNIT_CODE": "10113562"
    },
    {
      "TB_CODE": "13",
      "TB_FULL_NAME": "Центрально-Черноземный банк",
      "TB_SHORT_NAME": "ЦЧБ",
      "GOSB_CODE": "8596",
      "GOSB_NAME": "Курское ГОСБ",
      "GOSB_SHORT_NAME": "ГОСБ",
      "CLUSTER_CODE": "4",
      "GROUPING_CODE": "1",
      "GOSB_CNT": "9",
      "GROUPING_CNT": "9",
      "ORG_UNIT_CODE": "10016699"
    },
    {
      "TB_CODE": "13",
      "TB_FULL_NAME": "Центрально-Черноземный банк",
      "TB_SHORT_NAME": "ЦЧБ",
      "GOSB_CODE": "9013",
      "GOSB_NAME": "ГО по Воронежской области",
      "GOSB_SHORT_NAME": "ГОСБ",
      "CLUSTER_CODE": "1",
      "GROUPING_CODE": "1",
      "GOSB_CNT": "36",
      "GROUPING_CNT": "36",
      "ORG_UNIT_CODE": "10016705"
    },
    {
      "TB_CODE": "13",
      "TB_FULL_NAME": "Центрально-Черноземный банк",
      "TB_SHORT_NAME": "ЦЧБ",
      "GOSB_CODE": "9014",
      "GOSB_NAME": "ГО по Луганской Народной Республике",
      "GOSB_SHORT_NAME": "ГОСБ",
      "CLUSTER_CODE": "1",
      "GROUPING_CODE": "1",
      "GOSB_CNT": "36",
      "GROUPING_CNT": "36",
      "ORG_UNIT_CODE": "10354601"
    },
    {
      "TB_CODE": "52",
      "TB_FULL_NAME": "Юго-Западный банк",
      "TB_SHORT_NAME": "ЮЗБ",
      "GOSB_CODE": "0",
      "GOSB_NAME": "Аппарат территориального банка",
      "GOSB_SHORT_NAME": "Аппарат ЮЗБ",
      "CLUSTER_CODE": "0",
      "GROUPING_CODE": "1",
      "GOSB_CNT": "0",
      "GROUPING_CNT": "0",
      "ORG_UNIT_CODE": "10101758"
    },
    {
      "TB_CODE": "52",
      "TB_FULL_NAME": "Юго-Западный банк",
      "TB_SHORT_NAME": "ЮЗБ",
      "GOSB_CODE": "1806",
      "GOSB_NAME": "Центральное ГОСБ",
      "GOSB_SHORT_NAME": "ГОСБ",
      "CLUSTER_CODE": "5",
      "GROUPING_CODE": "1",
      "GOSB_CNT": "0",
      "GROUPING_CNT": "0",
      "ORG_UNIT_CODE": "10102240"
    },
    {
      "TB_CODE": "52",
      "TB_FULL_NAME": "Юго-Западный банк",
      "TB_SHORT_NAME": "ЮЗБ",
      "GOSB_CODE": "5200",
      "GOSB_NAME": "ГО по Республике Крым",
      "GOSB_SHORT_NAME": "ГОСБ",
      "CLUSTER_CODE": "5",
      "GROUPING_CODE": "1",
      "GOSB_CNT": "10",
      "GROUPING_CNT": "20",
      "ORG_UNIT_CODE": "10337151"
    },
    {
      "TB_CODE": "52",
      "TB_FULL_NAME": "Юго-Западный банк",
      "TB_SHORT_NAME": "ЮЗБ",
      "GOSB_CODE": "5221",
      "GOSB_NAME": "Ростовское ГОСБ",
      "GOSB_SHORT_NAME": "ГОСБ",
      "CLUSTER_CODE": "1",
      "GROUPING_CODE": "1",
      "GOSB_CNT": "38",
      "GROUPING_CNT": "38",
      "ORG_UNIT_CODE": "10107257"
    },
    {
      "TB_CODE": "52",
      "TB_FULL_NAME": "Юго-Западный банк",
      "TB_SHORT_NAME": "ЮЗБ",
      "GOSB_CODE": "5230",
      "GOSB_NAME": "Ставропольское ГОСБ",
      "GOSB_SHORT_NAME": "ГОСБ",
      "CLUSTER_CODE": "1",
      "GROUPING_CODE": "1",
      "GOSB_CNT": "26",
      "GROUPING_CNT": "26",
      "ORG_UNIT_CODE": "10193863"
    },
    {
      "TB_CODE": "52",
      "TB_FULL_NAME": "Юго-Западный банк",
      "TB_SHORT_NAME": "ЮЗБ",
      "GOSB_CODE": "8579",
      "GOSB_NAME": "Калмыцкое ОСБ",
      "GOSB_SHORT_NAME": "ГОСБ",
      "CLUSTER_CODE": "5",
      "GROUPING_CODE": "1",
      "GOSB_CNT": "1",
      "GROUPING_CNT": "20",
      "ORG_UNIT_CODE": "10197395"
    },
    {
      "TB_CODE": "52",
      "TB_FULL_NAME": "Юго-Западный банк",
      "TB_SHORT_NAME": "ЮЗБ",
      "GOSB_CODE": "8585",
      "GOSB_NAME": "Карачаево-Черкесское ОСБ",
      "GOSB_SHORT_NAME": "ГОСБ",
      "CLUSTER_CODE": "5",
      "GROUPING_CODE": "1",
      "GOSB_CNT": "2",
      "GROUPING_CNT": "20",
      "ORG_UNIT_CODE": "10197516"
    },
    {
      "TB_CODE": "52",
      "TB_FULL_NAME": "Юго-Западный банк",
      "TB_SHORT_NAME": "ЮЗБ",
      "GOSB_CODE": "8590",
      "GOSB_NAME": "Дагестанское ОСБ",
      "GOSB_SHORT_NAME": "ГОСБ",
      "CLUSTER_CODE": "3",
      "GROUPING_CODE": "1",
      "GOSB_CNT": "4",
      "GROUPING_CNT": "4",
      "ORG_UNIT_CODE": "10196938"
    },
    {
      "TB_CODE": "52",
      "TB_FULL_NAME": "Юго-Западный банк",
      "TB_SHORT_NAME": "ЮЗБ",
      "GOSB_CODE": "8619",
      "GOSB_NAME": "Краснодарское ГОСБ",
      "GOSB_SHORT_NAME": "ГОСБ",
      "CLUSTER_CODE": "1",
      "GROUPING_CODE": "1",
      "GOSB_CNT": "48",
      "GROUPING_CNT": "48",
      "ORG_UNIT_CODE": "10103881"
    },
    {
      "TB_CODE": "52",
      "TB_FULL_NAME": "Юго-Западный банк",
      "TB_SHORT_NAME": "ЮЗБ",
      "GOSB_CODE": "8620",
      "GOSB_NAME": "Адыгейское ГОСБ",
      "GOSB_SHORT_NAME": "ГОСБ",
      "CLUSTER_CODE": "5",
      "GROUPING_CODE": "1",
      "GOSB_CNT": "0",
      "GROUPING_CNT": "0",
      "ORG_UNIT_CODE": "10102854"
    },
    {
      "TB_CODE": "52",
      "TB_FULL_NAME": "Юго-Западный банк",
      "TB_SHORT_NAME": "ЮЗБ",
      "GOSB_CODE": "8631",
      "GOSB_NAME": "Кабардино-Балкарское ОСБ",
      "GOSB_SHORT_NAME": "ГОСБ",
      "CLUSTER_CODE": "5",
      "GROUPING_CODE": "1",
      "GOSB_CNT": "3",
      "GROUPING_CNT": "20",
      "ORG_UNIT_CODE": "10197168"
    },
    {
      "TB_CODE": "52",
      "TB_FULL_NAME": "Юго-Западный банк",
      "TB_SHORT_NAME": "ЮЗБ",
      "GOSB_CODE": "8632",
      "GOSB_NAME": "Северо-Осетинское ОСБ",
      "GOSB_SHORT_NAME": "ГОСБ",
      "CLUSTER_CODE": "5",
      "GROUPING_CODE": "1",
      "GOSB_CNT": "2",
      "GROUPING_CNT": "20",
      "ORG_UNIT_CODE": "10197647"
    },
    {
      "TB_CODE": "52",
      "TB_FULL_NAME": "Юго-Западный банк",
      "TB_SHORT_NAME": "ЮЗБ",
      "GOSB_CODE": "8633",
      "GOSB_NAME": "Ингушское ОСБ",
      "GOSB_SHORT_NAME": "ГОСБ",
      "CLUSTER_CODE": "5",
      "GROUPING_CODE": "1",
      "GOSB_CNT": "1",
      "GROUPING_CNT": "20",
      "ORG_UNIT_CODE": "10197087"
    },
    {
      "TB_CODE": "52",
      "TB_FULL_NAME": "Юго-Западный банк",
      "TB_SHORT_NAME": "ЮЗБ",
      "GOSB_CODE": "8643",
      "GOSB_NAME": "Чеченское ОСБ",
      "GOSB_SHORT_NAME": "ГОСБ",
      "CLUSTER_CODE": "5",
      "GROUPING_CODE": "1",
      "GOSB_CNT": "1",
      "GROUPING_CNT": "20",
      "ORG_UNIT_CODE": "10197789"
    },
    {
      "TB_CODE": "52",
      "TB_FULL_NAME": "Юго-Западный банк",
      "TB_SHORT_NAME": "ЮЗБ",
      "GOSB_CODE": "9052",
      "GOSB_NAME": "Аппарат Юго-Западного банка",
      "GOSB_SHORT_NAME": "ЦПКК ЮЗБ",
      "CLUSTER_CODE": "1",
      "GROUPING_CODE": "1",
      "GOSB_CNT": "14",
      "GROUPING_CNT": "14",
      "ORG_UNIT_CODE": "10295859"
    },
    {
      "TB_CODE": "52",
      "TB_FULL_NAME": "Юго-Западный банк",
      "TB_SHORT_NAME": "ЮЗБ",
      "GOSB_CODE": "9053",
      "GOSB_NAME": "ГО по Донецкой Народной Республике",
      "GOSB_SHORT_NAME": "ГОСБ",
      "CLUSTER_CODE": "1",
      "GROUPING_CODE": "1",
      "GOSB_CNT": "14",
      "GROUPING_CNT": "14",
      "ORG_UNIT_CODE": "10354600"
    }
  ]
}
